loc/__init__.py
loc/__init__.pyc
loc/compat.py
loc/compat.pyc
loc/loc_dict.py
loc/loc_dict.pyc
loc/locales.py
loc/locales.pyc
loc/__pycache__/__init__.cpython-34.pyc
loc/__pycache__/__init__.cpython-35.pyc
loc/__pycache__/__init__.cpython-36.pyc
loc/__pycache__/compat.cpython-34.pyc
loc/__pycache__/compat.cpython-35.pyc
loc/__pycache__/compat.cpython-36.pyc
loc/__pycache__/loc_dict.cpython-34.pyc
loc/__pycache__/loc_dict.cpython-35.pyc
loc/__pycache__/loc_dict.cpython-36.pyc
loc/__pycache__/locales.cpython-34.pyc
loc/__pycache__/locales.cpython-35.pyc
loc/__pycache__/locales.cpython-36.pyc
loc-0.0.2.dist-info/LICENSE.txt
loc-0.0.2.dist-info/METADATA
loc-0.0.2.dist-info/WHEEL
loc-0.0.2.dist-info/top_level.txt
loc-0.0.2.dist-info/RECORD
